recipies/__init__.py
recipies/constants.py
recipies/ingredients.py
recipies/recipe.py
recipies/selector.py
recipies/step.py
recipies-1.3.0.dist-info/licenses/LICENSE
recipies-1.3.0.dist-info/METADATA
recipies-1.3.0.dist-info/WHEEL
recipies-1.3.0.dist-info/top_level.txt
recipies-1.3.0.dist-info/RECORD
