Metadata-Version: 2.4
Name: recipies
Version: 1.3.0
Summary: A modular preprocessing package for Pandas Dataframe
Author: Hendrik Schmidt, Patrick Rockenschaub
Author-email: Robin van de Water <robin.vandewater@hpi.de>
License: MIT license
Keywords: recipies,pandas,dataframe,polars,preprocessing,recipys
Classifier: Development Status :: 4 - Beta
Classifier: Intended Audience :: Developers
Classifier: License :: OSI Approved :: MIT License
Classifier: Natural Language :: English
Classifier: Operating System :: OS Independent
Classifier: Programming Language :: Python :: 3.13
Classifier: Programming Language :: Python :: 3.12
Classifier: Programming Language :: Python :: 3.11
Classifier: Programming Language :: Python :: 3.10
Classifier: Programming Language :: Python :: 3.9
License-File: LICENSE
Requires-Dist: pandas>=2.3.0
Requires-Dist: polars[all]>=1.21.0
Requires-Dist: scikit-learn>=1.5.2
Provides-Extra: dev
Requires-Dist: pytest>=7.0; extra == "dev"
Requires-Dist: ruff>=0.1.0; extra == "dev"
Requires-Dist: pytest-cov; extra == "dev"
Provides-Extra: docs
Requires-Dist: mkdocs>=1.6; extra == "docs"
Requires-Dist: mkdocs-material>=9.5; extra == "docs"
Requires-Dist: mkdocstrings[python]>=0.26; extra == "docs"
Requires-Dist: mkdocs-autorefs>=1.0; extra == "docs"
Requires-Dist: pymdown-extensions>=10.8; extra == "docs"
Requires-Dist: mkdocs-jupyter>=0.24; extra == "docs"
Dynamic: license-file
